romullo_distribution/Binomialdistribution.py
romullo_distribution/Gaussiandistribution.py
romullo_distribution/Generaldistribution.py
romullo_distribution/__init__.py
romullo_distribution-1.0.dist-info/DESCRIPTION.rst
romullo_distribution-1.0.dist-info/METADATA
romullo_distribution-1.0.dist-info/RECORD
romullo_distribution-1.0.dist-info/WHEEL
romullo_distribution-1.0.dist-info/metadata.json
romullo_distribution-1.0.dist-info/top_level.txt
