Metadata-Version: 2.0
Name: romullo-distribution
Version: 1.0
Summary: Gaussian and Binomial distributions
Home-page: UNKNOWN
Author: Romullo Ferreira
Author-email: romulloferreira@gmail.com
License: UNKNOWN
Platform: UNKNOWN
